napari_trackpy/__init__.py
napari_trackpy/_version.py
napari_trackpy/_widget.py
napari_trackpy/_writer.py
napari_trackpy/napari.yaml
napari_trackpy/_tests/__init__.py
napari_trackpy/_tests/test_placeholder.py
napari_trackpy-0.3.0.dist-info/LICENSE
napari_trackpy-0.3.0.dist-info/METADATA
napari_trackpy-0.3.0.dist-info/WHEEL
napari_trackpy-0.3.0.dist-info/entry_points.txt
napari_trackpy-0.3.0.dist-info/top_level.txt
napari_trackpy-0.3.0.dist-info/RECORD
