Metadata-Version: 2.1
Name: napari-trackpy
Version: 0.3.0
Summary: Plugin to do trackpy particle tracking on microscopy data within napari
Home-page: https://github.com/rhoitink/napari-trackpy
Author: Roy Hoitink
Author-email: L.D.Hoitink@uu.nl
License: MIT
Project-URL: Bug Tracker, https://github.com/rhoitink/napari-trackpy/issues
Project-URL: Documentation, https://github.com/rhoitink/napari-trackpy#README.md
Project-URL: Source Code, https://github.com/rhoitink/napari-trackpy
Project-URL: User Support, https://github.com/rhoitink/napari-trackpy/issues
Classifier: Development Status :: 2 - Pre-Alpha
Classifier: Framework :: napari
Classifier: Intended Audience :: Developers
Classifier: License :: OSI Approved :: MIT License
Classifier: Operating System :: OS Independent
Classifier: Programming Language :: Python
Classifier: Programming Language :: Python :: 3
Classifier: Programming Language :: Python :: 3 :: Only
Classifier: Programming Language :: Python :: 3.8
Classifier: Programming Language :: Python :: 3.9
Classifier: Programming Language :: Python :: 3.10
Classifier: Programming Language :: Python :: 3.11
Classifier: Topic :: Scientific/Engineering :: Image Processing
Requires-Python: >=3.8
License-File: LICENSE
Requires-Dist: numpy
Requires-Dist: magicgui
Requires-Dist: qtpy
Requires-Dist: napari
Requires-Dist: napari-aicsimageio
Requires-Dist: readlif
Requires-Dist: trackpy
Requires-Dist: matplotlib
Provides-Extra: testing
Requires-Dist: tox ; extra == 'testing'
Requires-Dist: pytest ; extra == 'testing'
Requires-Dist: pytest-cov ; extra == 'testing'
Requires-Dist: pytest-qt ; extra == 'testing'
Requires-Dist: napari ; extra == 'testing'
Requires-Dist: pyqt5 ; extra == 'testing'
